serena_cli/__init__.py
serena_cli/cli.py
serena_cli/config_manager.py
serena_cli/mcp_server.py
serena_cli/project_detector.py
serena_cli/py.typed
serena_cli/serena_manager.py
serena_cli-1.0.12.dist-info/licenses/LICENSE
serena_cli-1.0.12.dist-info/METADATA
serena_cli-1.0.12.dist-info/WHEEL
serena_cli-1.0.12.dist-info/entry_points.txt
serena_cli-1.0.12.dist-info/top_level.txt
serena_cli-1.0.12.dist-info/RECORD
