Metadata-Version: 2.4
Name: serena-cli
Version: 1.0.12
Summary: A powerful CLI tool for quickly enabling and configuring Serena coding agent tools in specified projects
Author-email: Panda <panda@example.com>
Maintainer-email: Panda <panda@example.com>
License: MIT
Project-URL: Homepage, https://github.com/impanda-cookie/serena-cli
Project-URL: Documentation, https://github.com/impanda-cookie/serena-cli#readme
Project-URL: Repository, https://github.com/impanda-cookie/serena-cli
Project-URL: Issues, https://github.com/impanda-cookie/serena-cli/issues
Project-URL: Changelog, https://github.com/impanda-cookie/serena-cli/blob/main/CHANGELOG.md
Project-URL: Download, https://pypi.org/project/serena-cli/#files
Keywords: serena,cli,mcp,coding-agent,ai-tools,project-management
Classifier: Development Status :: 4 - Beta
Classifier: Intended Audience :: Developers
Classifier: License :: OSI Approved :: MIT License
Classifier: Operating System :: OS Independent
Classifier: Programming Language :: Python :: 3
Classifier: Programming Language :: Python :: 3.8
Classifier: Programming Language :: Python :: 3.9
Classifier: Programming Language :: Python :: 3.10
Classifier: Programming Language :: Python :: 3.11
Classifier: Programming Language :: Python :: 3.12
Classifier: Topic :: Software Development :: Libraries :: Python Modules
Classifier: Topic :: Software Development :: Libraries :: Application Frameworks
Classifier: Topic :: Utilities
Classifier: Environment :: Console
Requires-Python: >=3.8
License-File: LICENSE
Requires-Dist: mcp>=1.0.0
Requires-Dist: pyyaml>=6.0
Requires-Dist: click>=8.0.0
Requires-Dist: rich>=13.0.0
Requires-Dist: psutil>=5.9.0
Provides-Extra: dev
Requires-Dist: pytest>=7.0.0; extra == "dev"
Requires-Dist: pytest-cov>=4.0.0; extra == "dev"
Requires-Dist: black>=23.0.0; extra == "dev"
Requires-Dist: isort>=5.12.0; extra == "dev"
Requires-Dist: flake8>=6.0.0; extra == "dev"
Requires-Dist: mypy>=1.0.0; extra == "dev"
Requires-Dist: pre-commit>=3.0.0; extra == "dev"
Provides-Extra: test
Requires-Dist: pytest>=7.0.0; extra == "test"
Requires-Dist: pytest-cov>=4.0.0; extra == "test"
Requires-Dist: pytest-asyncio>=0.21.0; extra == "test"
Provides-Extra: docs
Requires-Dist: sphinx>=6.0.0; extra == "docs"
Requires-Dist: sphinx-rtd-theme>=1.2.0; extra == "docs"
Requires-Dist: myst-parser>=1.0.0; extra == "docs"
Dynamic: license-file
